nibetaseries/__init__.py
nibetaseries/_version.py
nibetaseries/conftest.py
nibetaseries/cli/__init__.py
nibetaseries/cli/run.py
nibetaseries/cli/tests/__init__.py
nibetaseries/cli/tests/test_run.py
nibetaseries/data/bids.json
nibetaseries/data/derivatives.json
nibetaseries/data/references.bib
nibetaseries/interfaces/__init__.py
nibetaseries/interfaces/bids.py
nibetaseries/interfaces/nilearn.py
nibetaseries/interfaces/nistats.py
nibetaseries/interfaces/tests/__init__.py
nibetaseries/interfaces/tests/test_bids.py
nibetaseries/interfaces/tests/test_nilearn.py
nibetaseries/interfaces/tests/test_nistats.py
nibetaseries/workflows/__init__.py
nibetaseries/workflows/analysis.py
nibetaseries/workflows/base.py
nibetaseries/workflows/model.py
nibetaseries/workflows/utils.py
nibetaseries/workflows/tests/__init__.py
nibetaseries/workflows/tests/test_base.py
nibetaseries/workflows/tests/test_utils.py
nibetaseries-0.6.0.dist-info/AUTHORS.rst
nibetaseries-0.6.0.dist-info/LICENSE
nibetaseries-0.6.0.dist-info/METADATA
nibetaseries-0.6.0.dist-info/WHEEL
nibetaseries-0.6.0.dist-info/entry_points.txt
nibetaseries-0.6.0.dist-info/top_level.txt
nibetaseries-0.6.0.dist-info/RECORD
