Metadata-Version: 2.1
Name: nibetaseries
Version: 0.6.0
Summary: BetaSeries Correlations implemented in Nipype
Home-page: https://github.com/HBClab/NiBetaSeries
Author: James Kent
Author-email: james-kent@uiowa.edu
Maintainer: James Kent
Maintainer-email: james-kent@uiowa.edu
License: UNKNOWN
Keywords: bids,fmri,neuroimaging
Platform: UNKNOWN
Classifier: Development Status :: 1 - Planning
Classifier: Environment :: Console
Classifier: Intended Audience :: Science/Research
Classifier: License :: OSI Approved :: MIT License
Classifier: Operating System :: Unix
Classifier: Operating System :: POSIX
Classifier: Programming Language :: Python
Classifier: Programming Language :: Python :: 3.5
Classifier: Programming Language :: Python :: 3.6
Classifier: Programming Language :: Python :: 3.7
Classifier: Topic :: Utilities
Requires-Python: >=3.5
Requires-Dist: nipype (~=1.4.2)
Requires-Dist: pybids (~=0.9.3)
Requires-Dist: nibabel (~=2.4.0)
Requires-Dist: nistats (==0.0.1b2)
Requires-Dist: nilearn (~=0.4.2)
Requires-Dist: pandas (~=0.24.0)
Requires-Dist: numpy
Requires-Dist: niworkflows (~=1.0.2)
Requires-Dist: duecredit (~=0.6.4)
Requires-Dist: scikit-learn (~=0.19.2)
Requires-Dist: matplotlib (~=2.2.4)
Requires-Dist: mne (~=0.18.1)
Requires-Dist: pypiwin32 ; platform_system == "Windows"
Provides-Extra: all
Requires-Dist: tox ; extra == 'all'
Requires-Dist: pytest (~=5.0.1) ; extra == 'all'
Requires-Dist: pytest-travis-fold ; extra == 'all'
Requires-Dist: pytest-cov ; extra == 'all'
Requires-Dist: seaborn ; extra == 'all'
Requires-Dist: pillow ; extra == 'all'
Requires-Dist: sphinx (<3,>2) ; extra == 'all'
Requires-Dist: sphinx-rtd-theme ; extra == 'all'
Requires-Dist: sphinx-argparse ; extra == 'all'
Requires-Dist: sphinx-gallery ; extra == 'all'
Requires-Dist: sphinxcontrib-bibtex ; extra == 'all'
Requires-Dist: check-manifest ; extra == 'all'
Requires-Dist: flake8 ; extra == 'all'
Requires-Dist: codecov ; extra == 'all'
Requires-Dist: coverage ; extra == 'all'
Provides-Extra: binder
Requires-Dist: sphinx (<3,>2) ; extra == 'binder'
Requires-Dist: sphinx-rtd-theme ; extra == 'binder'
Requires-Dist: sphinx-argparse ; extra == 'binder'
Requires-Dist: sphinx-gallery ; extra == 'binder'
Requires-Dist: sphinxcontrib-bibtex ; extra == 'binder'
Requires-Dist: seaborn ; extra == 'binder'
Requires-Dist: pillow ; extra == 'binder'
Requires-Dist: jupytext ; extra == 'binder'
Provides-Extra: dev
Requires-Dist: check-manifest ; extra == 'dev'
Requires-Dist: flake8 ; extra == 'dev'
Requires-Dist: codecov ; extra == 'dev'
Requires-Dist: coverage ; extra == 'dev'
Provides-Extra: doc
Requires-Dist: sphinx (<3,>2) ; extra == 'doc'
Requires-Dist: sphinx-rtd-theme ; extra == 'doc'
Requires-Dist: sphinx-argparse ; extra == 'doc'
Requires-Dist: sphinx-gallery ; extra == 'doc'
Requires-Dist: sphinxcontrib-bibtex ; extra == 'doc'
Provides-Extra: docs
Requires-Dist: sphinx (<3,>2) ; extra == 'docs'
Requires-Dist: sphinx-rtd-theme ; extra == 'docs'
Requires-Dist: sphinx-argparse ; extra == 'docs'
Requires-Dist: sphinx-gallery ; extra == 'docs'
Requires-Dist: sphinxcontrib-bibtex ; extra == 'docs'
Provides-Extra: nb
Requires-Dist: seaborn ; extra == 'nb'
Requires-Dist: pillow ; extra == 'nb'
Provides-Extra: test
Requires-Dist: tox ; extra == 'test'
Requires-Dist: pytest (~=5.0.1) ; extra == 'test'
Requires-Dist: pytest-travis-fold ; extra == 'test'
Requires-Dist: pytest-cov ; extra == 'test'
Provides-Extra: tests
Requires-Dist: tox ; extra == 'tests'
Requires-Dist: pytest (~=5.0.1) ; extra == 'tests'
Requires-Dist: pytest-travis-fold ; extra == 'tests'
Requires-Dist: pytest-cov ; extra == 'tests'
